howfairis/__init__.py
howfairis/__version__.py
howfairis/checker.py
howfairis/code_repository_platforms.py
howfairis/compliance.py
howfairis/get_apikeys_from_env_vars.py
howfairis/readme.py
howfairis/readme_format.py
howfairis/repo.py
howfairis/schema.py
howfairis/cli/__init__.py
howfairis/cli/cli.py
howfairis/cli/print_call_to_action.py
howfairis/cli/print_default_config.py
howfairis/cli/print_feedback_about_config_args.py
howfairis/cli/print_feedback_about_repo_args.py
howfairis/cli/print_version.py
howfairis/data/.howfairis.yml
howfairis/exceptions/__init__.py
howfairis/exceptions/get_default_branch_exception.py
howfairis/exceptions/howfairis_exception.py
howfairis/exceptions/howfairis_unknown_platform_exception.py
howfairis/mixins/__init__.py
howfairis/mixins/checklist_mixin.py
howfairis/mixins/citation_mixin.py
howfairis/mixins/license_mixin.py
howfairis/mixins/registry_mixin.py
howfairis/mixins/repository_mixin.py
howfairis/requesting/__init__.py
howfairis/requesting/get_from_github.py
howfairis/requesting/get_from_github_no_auth.py
howfairis/requesting/get_from_github_no_auth_api.py
howfairis/requesting/get_from_github_no_auth_frontend.py
howfairis/requesting/get_from_github_no_auth_raw.py
howfairis/requesting/get_from_github_with_auth.py
howfairis/requesting/get_from_github_with_auth_api.py
howfairis/requesting/get_from_github_with_auth_frontend.py
howfairis/requesting/get_from_github_with_auth_raw.py
howfairis/requesting/get_from_gitlab.py
howfairis/requesting/get_from_gitlab_no_auth.py
howfairis/requesting/get_from_gitlab_no_auth_api.py
howfairis/requesting/get_from_gitlab_no_auth_frontend.py
howfairis/requesting/get_from_gitlab_no_auth_raw.py
howfairis/requesting/get_from_gitlab_with_auth.py
howfairis/requesting/get_from_gitlab_with_auth_api.py
howfairis/requesting/get_from_gitlab_with_auth_frontend.py
howfairis/requesting/get_from_gitlab_with_auth_raw.py
howfairis/requesting/get_from_platform.py
howfairis/workarounds/__init__.py
howfairis-0.14.2.dist-info/LICENSE
howfairis-0.14.2.dist-info/METADATA
howfairis-0.14.2.dist-info/NOTICE
howfairis-0.14.2.dist-info/WHEEL
howfairis-0.14.2.dist-info/entry_points.txt
howfairis-0.14.2.dist-info/top_level.txt
howfairis-0.14.2.dist-info/RECORD
