Metadata-Version: 2.1
Name: howfairis
Version: 0.14.2
Summary: Python package to analyze compliance with fair-software.eu recommendations
Home-page: https://github.com/fair-software/howfairis
Author: https://github.com/jspaaks
Author-email: j.spaaks@esciencecenter.nl
License: Apache Software License 2.0
Keywords: howfairis
Classifier: Development Status :: 2 - Pre-Alpha
Classifier: Intended Audience :: Developers
Classifier: License :: OSI Approved :: Apache Software License
Classifier: Natural Language :: English
Classifier: Programming Language :: Python :: 3
Classifier: Programming Language :: Python :: 3.7
Classifier: Programming Language :: Python :: 3.8
Classifier: Programming Language :: Python :: 3.9
Classifier: Programming Language :: Python :: 3.10
License-File: LICENSE
License-File: NOTICE
Requires-Dist: backoff (==1.*)
Requires-Dist: beautifulsoup4 (==4.*)
Requires-Dist: click (==7.*)
Requires-Dist: colorama (==0.*)
Requires-Dist: docutils (==0.16.*)
Requires-Dist: pygments (==2.*)
Requires-Dist: ratelimit (==2.*)
Requires-Dist: requests (==2.*)
Requires-Dist: ruamel.yaml (==0.16.*)
Requires-Dist: voluptuous (==0.11.*)
Provides-Extra: dev
Requires-Dist: bumpversion ; extra == 'dev'
Requires-Dist: prospector[with_pyroma] ; extra == 'dev'
Requires-Dist: pycodestyle ; extra == 'dev'
Requires-Dist: pytest-cov ; extra == 'dev'
Requires-Dist: pytest-runner ; extra == 'dev'
Requires-Dist: pytest ; extra == 'dev'
Requires-Dist: recommonmark ; extra == 'dev'
Requires-Dist: requests-mock ; extra == 'dev'
Requires-Dist: sphinx-rtd-theme ; extra == 'dev'
Requires-Dist: sphinx-click ; extra == 'dev'
Requires-Dist: sphinx ; extra == 'dev'
Requires-Dist: yapf ; extra == 'dev'
Provides-Extra: publishing
Requires-Dist: twine ; extra == 'publishing'
Requires-Dist: wheel ; extra == 'publishing'
